utils_qt_mk/__init__.py
utils_qt_mk/_general.py
utils_qt_mk/colour_list.json
utils_qt_mk/colours.py
utils_qt_mk/colours.pyi
utils_qt_mk/config.py
utils_qt_mk/creators.py
utils_qt_mk/custom_file_dialog.py
utils_qt_mk/custom_file_dialog.pyi
utils_qt_mk/custom_file_dialog_data.json
utils_qt_mk/dynamic_attributes_collection.py
utils_qt_mk/general.py
utils_qt_mk/message.py
utils_qt_mk/message.pyi
utils_qt_mk/messagebox_types.json
utils_qt_mk/progress_dialog.py
utils_qt_mk/theme.py
utils_qt_mk/theme.pyi
utils_qt_mk/theme_creator.py
utils_qt_mk/theme_creator.pyi
utils_qt_mk/widget_mix.py
utils_qt_mk-1.1.0.dist-info/LICENSE
utils_qt_mk-1.1.0.dist-info/METADATA
utils_qt_mk-1.1.0.dist-info/WHEEL
utils_qt_mk-1.1.0.dist-info/top_level.txt
utils_qt_mk-1.1.0.dist-info/RECORD
