Metadata-Version: 2.2
Name: utils_qt_mk
Version: 1.1.0
Summary: Collection of utilities for Qt applications
Home-page: https://github.com/PzKpfwIVB/Utilities
Author: Mihaly Konda
Author-email: mihaly.konda@gmail.com
Classifier: Programming Language :: Python :: 3.12
Classifier: License :: OSI Approved :: GNU General Public License v3 (GPLv3)
Classifier: Operating System :: OS Independent
Requires-Python: >= 3.12
License-File: LICENSE
Requires-Dist: PySide6==6.6.2
Provides-Extra: dev
Requires-Dist: twine>=6.1.0; extra == "dev"
Dynamic: author
Dynamic: author-email
Dynamic: classifier
Dynamic: description
Dynamic: description-content-type
Dynamic: home-page
Dynamic: provides-extra
Dynamic: requires-dist
Dynamic: requires-python
Dynamic: summary
